kirami_plugin_helloworld-0.1.0.dist-info/METADATA
kirami_plugin_helloworld-0.1.0.dist-info/WHEEL
kirami_plugin_helloworld-0.1.0.dist-info/licenses/LICENSE
kirami_plugin_helloworld/__init__.py
kirami_plugin_helloworld/service.toml
kirami_plugin_helloworld-0.1.0.dist-info/RECORD
