Metadata-Version: 2.1
Name: kirami-plugin-helloworld
Version: 0.1.0
Summary: KiramiBot Hello World
Author-Email: Akirami <Akiramiaya@outlook.com>
License: MIT
Project-URL: Homepage, https://github.com/A-kirami/kirami-plugin-helloworld
Project-URL: Repository, https://github.com/A-kirami/kirami-plugin-helloworld
Requires-Python: >=3.10
Requires-Dist: kiramibot>=0.0.0
